[{"inputs":[{"internalType":"contract IRegistryPermission","name":"_permissionManager","type":"address"}],"stateMutability":"nonpayable","type":"constructor"},{"anonymous":false,"inputs":[{"indexed":false,"internalType":"address","name":"operator","type":"address"},{"components":[{"internalType":"uint256","name":"X","type":"uint256"},{"internalType":"uint256","name":"Y","type":"uint256"}],"indexed":false,"internalType":"struct BN254.G1Point","name":"pubkeyG1","type":"tuple"},{"components":[{"internalType":"uint256[2]","name":"X","type":"uint256[2]"},{"internalType":"uint256[2]","name":"Y","type":"uint256[2]"}],"indexed":false,"internalType":"struct BN254.G2Point","name":"pubkeyG2","type":"tuple"}],"name":"NewPubkeyRegistration","type":"event"},{"anonymous":false,"inputs":[{"indexed":false,"internalType":"string","name":"","type":"string"}],"name":"log","type":"event"},{"anonymous":false,"inputs":[{"indexed":false,"internalType":"address","name":"","type":"address"}],"name":"log_address","type":"event"},{"anonymous":false,"inputs":[{"indexed":false,"internalType":"bytes","name":"","type":"bytes"}],"name":"log_bytes","type":"event"},{"anonymous":false,"inputs":[{"indexed":false,"internalType":"bytes32","name":"","type":"bytes32"}],"name":"log_bytes32","type":"event"},{"anonymous":false,"inputs":[{"indexed":false,"internalType":"int256","name":"","type":"int256"}],"name":"log_int","type":"event"},{"anonymous":false,"inputs":[{"indexed":false,"internalType":"string","name":"key","type":"string"},{"indexed":false,"internalType":"address","name":"val","type":"address"}],"name":"log_named_address","type":"event"},{"anonymous":false,"inputs":[{"indexed":false,"internalType":"string","name":"key","type":"string"},{"indexed":false,"internalType":"bytes","name":"val","type":"bytes"}],"name":"log_named_bytes","type":"event"},{"anonymous":false,"inputs":[{"indexed":false,"internalType":"string","name":"key","type":"string"},{"indexed":false,"internalType":"bytes32","name":"val","type":"bytes32"}],"name":"log_named_bytes32","type":"event"},{"anonymous":false,"inputs":[{"indexed":false,"internalType":"string","name":"key","type":"string"},{"indexed":false,"internalType":"int256","name":"val","type":"int256"},{"indexed":false,"internalType":"uint256","name":"decimals","type":"uint256"}],"name":"log_named_decimal_int","type":"event"},{"anonymous":false,"inputs":[{"indexed":false,"internalType":"string","name":"key","type":"string"},{"indexed":false,"internalType":"uint256","name":"val","type":"uint256"},{"indexed":false,"internalType":"uint256","name":"decimals","type":"uint256"}],"name":"log_named_decimal_uint","type":"event"},{"anonymous":false,"inputs":[{"indexed":false,"internalType":"string","name":"key","type":"string"},{"indexed":false,"internalType":"int256","name":"val","type":"int256"}],"name":"log_named_int","type":"event"},{"anonymous":false,"inputs":[{"indexed":false,"internalType":"string","name":"key","type":"string"},{"indexed":false,"internalType":"string","name":"val","type":"string"}],"name":"log_named_string","type":"event"},{"anonymous":false,"inputs":[{"indexed":false,"internalType":"string","name":"key","type":"string"},{"indexed":false,"internalType":"uint256","name":"val","type":"uint256"}],"name":"log_named_uint","type":"event"},{"anonymous":false,"inputs":[{"indexed":false,"internalType":"string","name":"","type":"string"}],"name":"log_string","type":"event"},{"anonymous":false,"inputs":[{"indexed":false,"internalType":"uint256","name":"","type":"uint256"}],"name":"log_uint","type":"event"},{"anonymous":false,"inputs":[{"indexed":false,"internalType":"bytes","name":"","type":"bytes"}],"name":"logs","type":"event"},{"inputs":[],"name":"IS_TEST","outputs":[{"internalType":"bool","name":"","type":"bool"}],"stateMutability":"view","type":"function"},{"inputs":[],"name":"failed","outputs":[{"internalType":"bool","name":"","type":"bool"}],"stateMutability":"nonpayable","type":"function"},{"inputs":[{"internalType":"address","name":"","type":"address"}],"name":"operatorToPubkeyHash","outputs":[{"internalType":"bytes32","name":"","type":"bytes32"}],"stateMutability":"view","type":"function"},{"inputs":[],"name":"permissionManager","outputs":[{"internalType":"contract IRegistryPermission","name":"","type":"address"}],"stateMutability":"view","type":"function"},{"inputs":[{"internalType":"bytes32","name":"","type":"bytes32"}],"name":"pubkeyHashToOperator","outputs":[{"internalType":"address","name":"","type":"address"}],"stateMutability":"view","type":"function"},{"inputs":[{"internalType":"uint256","name":"s","type":"uint256"},{"components":[{"internalType":"uint256","name":"X","type":"uint256"},{"internalType":"uint256","name":"Y","type":"uint256"}],"internalType":"struct BN254.G1Point","name":"rPoint","type":"tuple"},{"components":[{"internalType":"uint256","name":"X","type":"uint256"},{"internalType":"uint256","name":"Y","type":"uint256"}],"internalType":"struct BN254.G1Point","name":"pubkeyG1","type":"tuple"},{"components":[{"internalType":"uint256[2]","name":"X","type":"uint256[2]"},{"internalType":"uint256[2]","name":"Y","type":"uint256[2]"}],"internalType":"struct BN254.G2Point","name":"pubkeyG2","type":"tuple"}],"name":"registerBLSPublicKey","outputs":[],"stateMutability":"nonpayable","type":"function"}]